crystal_bases/__init__.py
crystal_bases/crystal/__init__.py
crystal_bases/crystal/add_graph.py
crystal_bases/crystal/crystal_graph.py
crystal_bases/crystal/crystal_structure.py
crystal_bases/crystal/highest_weight_crystal.py
crystal_bases/young/__init__.py
crystal_bases/young/jeu_de_taquin.py
crystal_bases/young/pr.py
crystal_bases/young/tableau.py
crystal_bases-0.1.0.dist-info/WHEEL
crystal_bases-0.1.0.dist-info/METADATA
crystal_bases-0.1.0.dist-info/RECORD
